<Ui xmlns="http://www.blizzard.com/wow/ui/" xmlns:xsi="http://www.w3.org/2001/XMLSchema-instance" xsi:schemaLocation="http://www.blizzard.com/wow/ui/
..\FrameXML\UI.xsd">

<!--@do-not-package@-->
<Include file="Classic\modules.xml"/>
<Include file="TBC\modules.xml"/>
<Include file="WotLK\modules.xml"/>
<Include file="Cataclysm\modules.xml"/>
<Include file="MoP\modules.xml"/>
<Include file="WoD\modules.xml"/>
<Include file="Legion\modules.xml"/>
<Include file="BfA\modules.xml"/>
<Include file="Shadowlands\modules.xml"/>
<!--@end-do-not-package@-->
<Include file="Dragonflight\modules.xml"/>

</Ui>
